lmarv-1/tester/fpga-tester-1/shift_controller.v
module shift_controller(
  input go_read,         // Signal to start reading
  input go_write,        // Signal to start writing
  input ready_read,      // Signal that ready for read
  input ready_write,     // Signal that ready for write
  input read_shift_clk,  // Signal to shift for read
  input write_shift_clk, // Signal to shift for write
  output go_read_out,    // Arbritrated start reading
  output go_write_out,   // Arbritrated start writing
  output shift_clk       // Arbitrated shift clock
);

  assign go_read_out = go_read && ready_read && ready_write;
  assign go_write_out = go_write && ready_read && ready_write && !go_read;
  assign shift_clk = write_shift_clk || read_shift_clk;

endmodule

lmarv-1/tester/fpga-tester-1/shift_in.v
module shift_in(
  input clk,           // 16MHz global clock
  input action_pulse,  // 1MHz global action pulse, for setting things up before the
                       // positive edge of action_clk
  input action_clk,    // 1MHz action clock, toggles after action_pulse
  output reg [31:0] data = 0, // The data that was read in, valid on ready = 1
  input go,                 // The signal to start shifting
  output read_load_clk,     // Loads the shifter inputs
  output reg shift_clk = 0, // Shifts the data out of the shifter
  input serial_data_in,     // The read from the shifter
  output ready              // The ready signal
);

  reg [5:0] cycle_counter = 0;
  reg active = 0;

  wire start = ready && go;
  assign ready = cycle_counter == 0 && !active;
  assign read_load_clk = cycle_counter == 6'd1;
  wire stop = cycle_counter == 6'd34;

  always @(posedge clk) begin
    if (start) active <= 1;
    else if (stop) active <= 0;
  end

  always @(posedge clk) begin
    if (cycle_counter >= 2 && cycle_counter <= 33) shift_clk <= action_clk;
    else shift_clk <= 0;
  end

  always @(posedge clk) begin
    if (action_pulse) begin
      if (start) cycle_counter <= 1;
      else if (stop) cycle_counter <= 0;
      else if (active) cycle_counter <= cycle_counter + 1;
    end
  end

  always @(posedge clk) begin
    if (start && action_pulse) data[31:0] <= 0;
    else if (active && action_pulse) begin
      data[31:1] <= data[30:0];
      data[0] <= serial_data_in;
    end
  end

endmodule

lmarv-1/tester/fpga-tester-1/shift_out.v
module shift_out(
  input clk,           // 16MHz global clock
  input action_pulse,  // 1MHz global action pulse, for setting things up before the
                       // positive edge of action_clk
  input action_clk,    // 1MHz action clock, toggles after action_pulse
  input load_data_clk,      // Loads data into this module
  input [31:0] load_data,   // The data to load into this module
  input go,                 // The signal to start shifting
  output write_load_clk,    // Loads the shifter outputs
  output reg shift_clk = 0, // Shifts the data into the shifter
  output serial_data_out,   // The data to shift into the shifter
  output ready              // The ready signal
);

  reg [32:0] data = 0;
  reg [5:0] cycle_counter = 0;
  reg active = 0;

  assign serial_data_out = data[32];

  wire start = ready && go;
  assign ready = cycle_counter == 0 && !active;
  assign write_load_clk = cycle_counter == 6'd33;
  wire stop = cycle_counter == 6'd34;

  always @(posedge clk) begin
    if (start) active <= 1;
    else if (stop) active <= 0;
  end

  always @(posedge clk) begin
    if (cycle_counter >= 1 && cycle_counter <= 32) shift_clk <= action_clk;
    else shift_clk <= 0;
  end

  always @(posedge clk) begin
    if (action_pulse) begin
      if (start) cycle_counter <= 1;
      else if (stop) cycle_counter <= 0;
      else if (active) cycle_counter <= cycle_counter + 1;
    end
  end

  always @(posedge clk) begin
    if (ready && !go && load_data_clk) begin
      data[31:0] <= load_data[31:0];
      data[32] <= 0;
    end else if (active && action_pulse) begin
      data[32:1] <= data[31:0];
      data[0] <= 0;
    end
  end

endmodule

lmarv-1/tester/fpga-tester-1/clocker.v
module clocker(
  input clk,            // 16MHz global clock
  output action_pulse,  // 1MHz global action pulse, for setting things up before the
                        // positive edge of action_clk
  output action_clk     // 1MHz clock, positive edge after action_pulse
);

reg [4:0] action_counter = 0;
assign action_pulse = action_counter[4:0] == 5'b01000;
assign action_clk = action_counter[4];

// increment counters
always @(posedge clk) begin
  action_counter <= action_counter + 1;
end

endmodule

lmarv-1/tester/fpga-tester-1/top.v
module shifter (
  input CLK,     // 16MHz clock
  output LED,    // User/boot LED next to power LED
  output USBPU,  // USB pull-up resistor
  output PIN_1,  // shift clock (CLK)
  output PIN_2,  // n_oe (nOE)
  output PIN_3,  // serial_write (SI)
  output PIN_4,  // write_load (WLD)
  output PIN_5,  // n_read_load (nRLD)
  input PIN_6    // serial_read (SO)
);

  // drive USB pull-up resistor to '0' to disable USB
  assign USBPU = 0;

  // rename pins
  wire shift_clock;
  reg n_oe = 1;
  wire serial_write;
  wire write_load_clk;
  wire n_read_load_clk;
  wire serial_read;
  assign PIN_1 = shift_clock;
  assign PIN_2 = n_oe;
  assign PIN_3 = serial_write;
  assign PIN_4 = write_load_clk;
  assign PIN_5 = n_read_load_clk;
  assign PIN_6 = serial_read;

  reg [31:0] output_data = 32'h8888060A;

  reg [31:0] input_data = 32'h00000000;
  reg [32:0] shift_data = 0;
  assign serial_write = shift_data[32];
  reg [33:0] write_load_shifter = 0;
  reg [34:0] read_load_shifter = 0;
  reg [66:0] shift_in_en = 67'hFFFFFFFF;
  wire shift_in;
  assign shift_in = shift_in_en[66];

  // Approximate 1Hz counter (actually 16777216/16000000 Hz)
  reg [24:0] counter = 25'h0FFFFFE;
  wire active;
  assign active = counter[24];
  assign LED = active;


  // 1MHz shift counter
  reg shift_clk_enable = 0;
  reg write_load_clk_enable = 0;
  reg read_load_clk_enable = 0;

  reg [4:0] shift_counter = 0;
  wire do_shift;
  assign do_shift = shift_counter[4:0] == 5'b01000;

  assign shift_clock = shift_clk_enable && shift_counter[4];
  assign write_load_clk = write_load_clk_enable && shift_counter[4];
  assign n_read_load_clk = !(read_load_clk_enable && shift_counter[4]);


  // increment counters
  always @(posedge CLK) begin
    shift_counter <= shift_counter + 1;
    counter <= counter + 1;
    if (write_load_clk_enable) n_oe <= 0;
  end

  always @(posedge CLK) begin
    shift_clk_enable <= !write_load_shifter[33] && !read_load_shifter[34];
    write_load_clk_enable <= write_load_shifter[33];
    read_load_clk_enable <= read_load_shifter[34];
    if (write_load_clk_enable && do_shift) output_data[31:0] <= ~output_data[31:0];
  end

  // shift in/out
  always @(posedge CLK) begin
    if (do_shift && active) begin
      shift_data[32:1] <= shift_data[31:0];
      shift_data[0] <= 0;
      write_load_shifter[33:1] <= write_load_shifter[32:0];
      write_load_shifter[0] <= 0;
      read_load_shifter[34:1] <= read_load_shifter[33:0];
      read_load_shifter[0] <= 0;
      shift_in_en[66:1] <= shift_in_en[65:0];
      shift_in_en[0] <= 0;
    end else if (!active) begin
      write_load_shifter[33] <= 0;
      write_load_shifter[32:0] <= 33'h1;
      read_load_shifter[34] <= 0;
      read_load_shifter[33:0] <= 34'h1;
      shift_data[32] <= 0;
      shift_data[31:0] <= output_data[31:0];
      shift_in_en[66:0] <= 67'hFFFFFFFF;
    end
  end

endmodule

lmarv-1/tester/fpga-tester-1/top_tb.v
`timescale 1ns / 1ns

`ifdef __ICARUS__
 `define finish_and_return(code) $finish_and_return(code)
`else
 `define finish_and_return(code) $finish
`endif

module top_tb;
    initial begin
      $dumpfile("top_tb.vcd");
      $dumpvars(0, top_tb);
      $dumpvars(0, dut);
      $dumpvars(0, clock_thing);
      $dumpvars(0, shift_out_thing);
      $dumpvars(0, shift_in_thing);
    end

    reg clk = 0;

    initial begin
      forever begin
        #1 clk <= !clk;
      end
    end

    wire led;
    wire shclk;
    wire n_oe;
    wire swr;
    wire wrld;
    wire usbpu;

    shifter dut(
      .CLK(clk),
      .USBPU(usbpu),
      .LED(led),
      .PIN_1(shclk),
      .PIN_2(n_oe),
      .PIN_3(swr),
      .PIN_4(wrld)
    );

    wire action_pulse;
    wire action_clk;

    clocker clock_thing(
      .clk(clk),
      .action_pulse(action_pulse),
      .action_clk(action_clk)
    );

    wire arb_read_go;
    wire arb_write_go;
    wire arb_shift_clk;

    reg load_data_clk = 0;
    reg [31:0] load_data = 32'h8F8F8FE1;
    reg write_go = 0;
    wire write_load_clk;
    wire write_shift_clk;
    wire serial_data_out;
    wire write_ready;

    shift_out shift_out_thing(
      .clk(clk),
      .action_pulse(action_pulse),
      .action_clk(action_clk),
      .load_data_clk(load_data_clk),
      .load_data(load_data),
      .go(arb_write_go),
      .write_load_clk(write_load_clk),
      .shift_clk(write_shift_clk),
      .serial_data_out(serial_data_out),
      .ready(write_ready)
    );

    initial begin
      #90 load_data_clk <= 1;
      #96 load_data_clk <= 0;
      #100 write_go <= 1;
    end

    wire [31:0] read_data;
    reg read_go = 0;
    wire read_load_clk;
    wire read_shift_clk;
    reg serial_data_in = 0;
    wire read_ready;
    reg [31:0] test_read_data = 32'h8F8F8FE1;
    reg [4:0] test_read_data_ptr = 5'd31;

    shift_in shift_in_thing(
      .clk(clk),
      .action_pulse(action_pulse),
      .action_clk(action_clk),
      .data(read_data),
      .go(arb_read_go),
      .read_load_clk(read_load_clk),
      .shift_clk(read_shift_clk),
      .serial_data_in(serial_data_in),
      .ready(read_ready)
    );

    initial begin
      #90 read_go <= 1;
    end

    always @(posedge read_shift_clk) begin
      serial_data_in <= test_read_data[test_read_data_ptr];
      test_read_data_ptr <= test_read_data_ptr - 1;
    end

    shift_controller controller(
      .go_read(read_go),
      .go_write(write_go),
      .ready_read(read_ready),
      .ready_write(write_ready),
      .read_shift_clk(read_shift_clk),
      .write_shift_clk(write_shift_clk),
      .go_read_out(arb_read_go),
      .go_write_out(arb_write_go),
      .shift_clk(arb_shift_clk)
    );

    initial begin
      #10000;
      $finish(0);
    end
endmodule

lmarv-1/tester/fpga-tester-1/top_tb.vcd
$date
	Sun Sep 23 14:51:02 2018
$end
$version
	Icarus Verilog
$end
$timescale
	1ns
$end
$scope module top_tb $end
$var wire 1 ! usbpu $end
$var wire 1 " wrld $end
$var wire 1 # write_shift_clk $end
$var wire 1 $ write_ready $end
$var wire 1 % write_load_clk $end
$var wire 1 & swr $end
$var wire 1 ' shclk $end
$var wire 1 ( serial_data_out $end
$var wire 1 ) read_shift_clk $end
$var wire 1 * read_ready $end
$var wire 1 + read_load_clk $end
$var wire 32 , read_data [31:0] $end
$var wire 1 - n_oe $end
$var wire 1 . led $end
$var wire 1 / arb_write_go $end
$var wire 1 0 arb_shift_clk $end
$var wire 1 1 arb_read_go $end
$var wire 1 2 action_pulse $end
$var wire 1 3 action_clk $end
$var reg 1 4 clk $end
$var reg 32 5 load_data [31:0] $end
$var reg 1 6 load_data_clk $end
$var reg 1 7 read_go $end
$var reg 1 8 serial_data_in $end
$var reg 32 9 test_read_data [31:0] $end
$var reg 5 : test_read_data_ptr [4:0] $end
$var reg 1 ; write_go $end
$scope module clock_thing $end
$var wire 1 4 clk $end
$var wire 1 2 action_pulse $end
$var wire 1 3 action_clk $end
$var reg 5 < action_counter [4:0] $end
$upscope $end
$scope module controller $end
$var wire 1 7 go_read $end
$var wire 1 1 go_read_out $end
$var wire 1 ; go_write $end
$var wire 1 / go_write_out $end
$var wire 1 0 shift_clk $end
$var wire 1 # write_shift_clk $end
$var wire 1 $ ready_write $end
$var wire 1 * ready_read $end
$var wire 1 ) read_shift_clk $end
$upscope $end
$scope module dut $end
$var wire 1 4 CLK $end
$var wire 1 . LED $end
$var wire 1 ' PIN_1 $end
$var wire 1 - PIN_2 $end
$var wire 1 & PIN_3 $end
$var wire 1 " PIN_4 $end
$var wire 1 = PIN_5 $end
$var wire 1 > PIN_6 $end
$var wire 1 ! USBPU $end
$var wire 1 ? serial_read $end
$var wire 1 @ shift_clock $end
$var wire 1 A write_load_clk $end
$var wire 1 B shift_in $end
$var wire 1 C serial_write $end
$var wire 1 D n_read_load_clk $end
$var wire 1 E do_shift $end
$var wire 1 F active $end
$var reg 25 G counter [24:0] $end
$var reg 32 H input_data [31:0] $end
$var reg 1 I n_oe $end
$var reg 32 J output_data [31:0] $end
$var reg 1 K read_load_clk_enable $end
$var reg 35 L read_load_shifter [34:0] $end
$var reg 1 M shift_clk_enable $end
$var reg 5 N shift_counter [4:0] $end
$var reg 33 O shift_data [32:0] $end
$var reg 67 P shift_in_en [66:0] $end
$var reg 1 Q write_load_clk_enable $end
$var reg 34 R write_load_shifter [33:0] $end
$upscope $end
$scope module shift_in_thing $end
$var wire 1 3 action_clk $end
$var wire 1 2 action_pulse $end
$var wire 1 4 clk $end
$var wire 1 1 go $end
$var wire 1 * ready $end
$var wire 1 8 serial_data_in $end
$var wire 1 S start $end
$var wire 1 T stop $end
$var wire 1 + read_load_clk $end
$var reg 1 U active $end
$var reg 6 V cycle_counter [5:0] $end
$var reg 32 W data [31:0] $end
$var reg 1 ) shift_clk $end
$upscope $end
$scope module shift_out_thing $end
$var wire 1 3 action_clk $end
$var wire 1 2 action_pulse $end
$var wire 1 4 clk $end
$var wire 1 / go $end
$var wire 32 X load_data [31:0] $end
$var wire 1 6 load_data_clk $end
$var wire 1 $ ready $end
$var wire 1 Y start $end
$var wire 1 % write_load_clk $end
$var wire 1 Z stop $end
$var wire 1 ( serial_data_out $end
$var reg 1 [ active $end
$var reg 6 \ cycle_counter [5:0] $end
$var reg 33 ] data [32:0] $end
$var reg 1 # shift_clk $end
$upscope $end
$upscope $end
$scope module top_tb $end
$scope module dut $end
$upscope $end
$upscope $end
$scope module top_tb $end
$scope module clock_thing $end
$upscope $end
$upscope $end
$scope module top_tb $end
$scope module shift_out_thing $end
$upscope $end
$upscope $end
$scope module top_tb $end
$scope module shift_in_thing $end
$upscope $end
$upscope $end
$enddefinitions $end
#0
$dumpvars
b0 ]
b0 \
0[
0Z
0Y
b10001111100011111000111111100001 X
b0 W
b0 V
0U
0T
0S
b0 R
0Q
b11111111111111111111111111111111 P
b0 O
b0 N
0M
b0 L
0K
b10001000100010000000011000001010 J
1I
b0 H
b111111111111111111111110 G
0F
0E
1D
0C
0B
0A
0@
z?
z>
1=
b0 <
0;
b11111 :
b10001111100011111000111111100001 9
08
07
06
b10001111100011111000111111100001 5
04
03
02
01
00
0/
0.
1-
b0 ,
0+
1*
0)
0(
0'
0&
0%
1$
0#
0"
0!
$end
#1
b111111111111111111111111 G
b1 N
1M
b10001000100010000000011000001010 O
b1 L
b1 R
b1 <
14
#2
04
#3
1.
1F
b10 <
b1000000000000000000000000 G
b10 N
14
#4
04
#5
b1000000000000000000000001 G
b11 N
b11 <
14
#6
04
#7
b100 <
b1000000000000000000000010 G
b100 N
14
#8
04
#9
b1000000000000000000000011 G
b101 N
b101 <
14
#10
04
#11
b110 <
b1000000000000000000000100 G
b110 N
14
#12
04
#13
b1000000000000000000000101 G
b111 N
b111 <
14
#14
04
#15
12
b1000 <
b1000000000000000000000110 G
1E
b1000 N
14
#16
04
#17
1&
1C
b1000000000000000000000111 G
0E
b1001 N
b111111111111111111111111111111110 P
b10 L
b10 R
b100010001000100000000110000010100 O
02
b1001 <
14
#18
04
#19
b1010 <
b1000000000000000000001000 G
b1010 N
14
#20
04
#21
b1000000000000000000001001 G
b1011 N
b1011 <
14
#22
04
#23
b1100 <
b1000000000000000000001010 G
b1100 N
14
#24
04
#25
b1000000000000000000001011 G
b1101 N
b1101 <
14
#26
04
#27
b1110 <
b1000000000000000000001100 G
b1110 N
14
#28
04
#29
b1000000000000000000001101 G
b1111 N
b1111 <
14
#30
04
#31
1'
1@
13
b10000 <
b1000000000000000000001110 G
b10000 N
14
#32
04
#33
b1000000000000000000001111 G
b10001 N
b10001 <
14
#34
04
#35
b10010 <
b1000000000000000000010000 G
b10010 N
14
#36
04
#37
b1000000000000000000010001 G
b10011 N
b10011 <
14
#38
04
#39
b10100 <
b1000000000000000000010010 G
b10100 N
14
#40
04
#41
b1000000000000000000010011 G
b10101 N
b10101 <
14
#42
04
#43
b10110 <
b1000000000000000000010100 G
b10110 N
14
#44
04
#45
b1000000000000000000010101 G
b10111 N
b10111 <
14
#46
04
#47
b11000 <
b1000000000000000000010110 G
b11000 N
14
#48
04
#49
b1000000000000000000010111 G
b11001 N
b11001 <
14
#50
04
#51
b11010 <
b1000000000000000000011000 G
b11010 N
14
#52
04
#53
b1000000000000000000011001 G
b11011 N
b11011 <
14
#54
04
#55
b11100 <
b1000000000000000000011010 G
b11100 N
14
#56
04
#57
b1000000000000000000011011 G
b11101 N
b11101 <
14
#58
04
#59
b11110 <
b1000000000000000000011100 G
b11110 N
14
#60
04
#61
b1000000000000000000011101 G
b11111 N
b11111 <
14
#62
04
#63
0'
0@
03
b0 <
b1000000000000000000011110 G
b0 N
14
#64
04
#65
b1000000000000000000011111 G
b1 N
b1 <
14
#66
04
#67
b10 <
b1000000000000000000100000 G
b10 N
14
#68
04
#69
b1000000000000000000100001 G
b11 N
b11 <
14
#70
04
#71
b100 <
b1000000000000000000100010 G
b100 N
14
#72
04
#73
b1000000000000000000100011 G
b101 N
b101 <
14
#74
04
#75
b110 <
b1000000000000000000100100 G
b110 N
14
#76
04
#77
b1000000000000000000100101 G
b111 N
b111 <
14
#78
04
#79
12
b1000 <
b1000000000000000000100110 G
1E
b1000 N
14
#80
04
#81
0&
0C
b1000000000000000000100111 G
0E
b1001 N
b1111111111111111111111111111111100 P
b100 L
b100 R
b100010001000000001100000101000 O
02
b1001 <
14
#82
04
#83
b1010 <
b1000000000000000000101000 G
b1010 N
14
#84
04
#85
b1000000000000000000101001 G
b1011 N
b1011 <
14
#86
04
#87
b1100 <
b1000000000000000000101010 G
b1100 N
14
#88
04
#89
b1000000000000000000101011 G
b1101 N
b1101 <
14
#90
1S
11
04
17
16
#91
01
0S
0*
1U
b10001111100011111000111111100001 ]
b1110 <
b1000000000000000000101100 G
b1110 N
14
#92
04
#93
b1000000000000000000101101 G
b1111 N
b1111 <
14
#94
04
#95
1'
1@
13
b10000 <
b1000000000000000000101110 G
b10000 N
14
#96
04
#97
b1000000000000000000101111 G
b10001 N
b10001 <
14
#98
04
#99
b10010 <
b1000000000000000000110000 G
b10010 N
14
#100
04
#101
b1000000000000000000110001 G
b10011 N
b10011 <
14
#102
04
#103
b10100 <
b1000000000000000000110010 G
b10100 N
14
#104
04
#105
b1000000000000000000110011 G
b10101 N
b10101 <
14
#106
04
#107
b10110 <
b1000000000000000000110100 G
b10110 N
14
#108
04
#109
b1000000000000000000110101 G
b10111 N
b10111 <
14
#110
04
#111
b11000 <
b1000000000000000000110110 G
b11000 N
14
#112
04
#113
b1000000000000000000110111 G
b11001 N
b11001 <
14
#114
04
#115
b11010 <
b1000000000000000000111000 G
b11010 N
14
#116
04
#117
b1000000000000000000111001 G
b11011 N
b11011 <
14
#118
04
#119
b11100 <
b1000000000000000000111010 G
b11100 N
14
#120
04
#121
b1000000000000000000111011 G
b11101 N
b11101 <
14
#122
04
#123
b11110 <
b1000000000000000000111100 G
b11110 N
14
#124
04
#125
b1000000000000000000111101 G
b11111 N
b11111 <
14
#126
04
#127
0'
0@
03
b0 <
b1000000000000000000111110 G
b0 N
14
#128
04
#129
b1000000000000000000111111 G
b1 N
b1 <
14
#130
04
#131
b10 <
b1000000000000000001000000 G
b10 N
14
#132
04
#133
b1000000000000000001000001 G
b11 N
b11 <
14
#134
04
#135
b100 <
b1000000000000000001000010 G
b100 N
14
#136
04
#137
b1000000000000000001000011 G
b101 N
b101 <
14
#138
04
#139
b110 <
b1000000000000000001000100 G
b110 N
14
#140
04
#141
b1000000000000000001000101 G
b111 N
b111 <
14
#142
04
#143
12
b1000 <
b1000000000000000001000110 G
1E
b1000 N
14
#144
04
#145
b1000000000000000001000111 G
0E
b1001 N
b11111111111111111111111111111111000 P
b1000 L
b1000 R
b1000100010000000011000001010000 O
02
b1001 <
1+
b1 V
14
#146
04
#147
b1010 <
b1000000000000000001001000 G
b1010 N
14
#148
04
#149
b1000000000000000001001001 G
b1011 N
b1011 <
14
#150
04
#151
b1100 <
b1000000000000000001001010 G
b1100 N
14
#152
04
#153
b1000000000000000001001011 G
b1101 N
b1101 <
14
#154
04
#155
b1110 <
b1000000000000000001001100 G
b1110 N
14
#156
04
#157
b1000000000000000001001101 G
b1111 N
b1111 <
14
#158
04
#159
1'
1@
13
b10000 <
b1000000000000000001001110 G
b10000 N
14
#160
04
#161
b1000000000000000001001111 G
b10001 N
b10001 <
14
#162
04
#163
b10010 <
b1000000000000000001010000 G
b10010 N
14
#164
04
#165
b1000000000000000001010001 G
b10011 N
b10011 <
14
#166
04
#167
b10100 <
b1000000000000000001010010 G
b10100 N
14
#168
04
#169
b1000000000000000001010011 G
b10101 N
b10101 <
14
#170
04
#171
b10110 <
b1000000000000000001010100 G
b10110 N
14
#172
04
#173
b1000000000000000001010101 G
b10111 N
b10111 <
14
#174
04
#175
b11000 <
b1000000000000000001010110 G
b11000 N
14
#176
04
#177
b1000000000000000001010111 G
b11001 N
b11001 <
14
#178
04
#179
b11010 <
b1000000000000000001011000 G
b11010 N
14
#180
04
#181
b1000000000000000001011001 G
b11011 N
b11011 <
14
#182
04
#183
b11100 <
b1000000000000000001011010 G
b11100 N
14
#184
04
#185
b1000000000000000001011011 G
b11101 N
b11101 <
14
#186
04
06
#187
b11110 <
b1000000000000000001011100 G
b11110 N
14
#188
04
#189
b1000000000000000001011101 G
b11111 N
b11111 <
14
#190
04
#191
0'
0@
03
b0 <
b1000000000000000001011110 G
b0 N
14
#192
04
#193
b1000000000000000001011111 G
b1 N
b1 <
14
#194
04
#195
b10 <
b1000000000000000001100000 G
b10 N
14
#196
04
#197
b1000000000000000001100001 G
b11 N
b11 <
14
#198
04
#199
b100 <
b1000000000000000001100010 G
b100 N
14
#200
04
#201
b1000000000000000001100011 G
b101 N
b101 <
14
#202
04
#203
b110 <
b1000000000000000001100100 G
b110 N
14
#204
04
#205
b1000000000000000001100101 G
b111 N
b111 <
14
#206
04
#207
12
b1000 <
b1000000000000000001100110 G
1E
b1000 N
14
#208
04
#209
b1000000000000000001100111 G
0E
b1001 N
b111111111111111111111111111111110000 P
b10000 L
b10000 R
b10001000100000000110000010100000 O
02
b1001 <
0+
b10 V
14
#210
04
#211
b1010 <
b1000000000000000001101000 G
b1010 N
14
#212
04
#213
b1000000000000000001101001 G
b1011 N
b1011 <
14
#214
04
#215
b1100 <
b1000000000000000001101010 G
b1100 N
14
#216
04
#217
b1000000000000000001101011 G
b1101 N
b1101 <
14
#218
04
#219
b1110 <
b1000000000000000001101100 G
b1110 N
14
#220
04
#221
b1000000000000000001101101 G
b1111 N
b1111 <
14
#222
04
#223
1'
1@
13
b10000 <
b1000000000000000001101110 G
b10000 N
14
#224
04
#225
b11110 :
18
10
b1000000000000000001101111 G
b10001 N
b10001 <
1)
14
#226
04
#227
b10010 <
b1000000000000000001110000 G
b10010 N
14
#228
04
#229
b1000000000000000001110001 G
b10011 N
b10011 <
14
#230
04
#231
b10100 <
b1000000000000000001110010 G
b10100 N
14
#232
04
#233
b1000000000000000001110011 G
b10101 N
b10101 <
14
#234
04
#235
b10110 <
b1000000000000000001110100 G
b10110 N
14
#236
04
#237
b1000000000000000001110101 G
b10111 N
b10111 <
14
#238
04
#239
b11000 <
b1000000000000000001110110 G
b11000 N
14
#240
04
#241
b1000000000000000001110111 G
b11001 N
b11001 <
14
#242
04
#243
b11010 <
b1000000000000000001111000 G
b11010 N
14
#244
04
#245
b1000000000000000001111001 G
b11011 N
b11011 <
14
#246
04
#247
b11100 <
b1000000000000000001111010 G
b11100 N
14
#248
04
#249
b1000000000000000001111011 G
b11101 N
b11101 <
14
#250
04
#251
b11110 <
b1000000000000000001111100 G
b11110 N
14
#252
04
#253
b1000000000000000001111101 G
b11111 N
b11111 <
14
#254
04
#255
0'
0@
03
b0 <
b1000000000000000001111110 G
b0 N
14
#256
04
#257
00
b1000000000000000001111111 G
b1 N
b1 <
0)
14
#258
04
#259
b10 <
b1000000000000000010000000 G
b10 N
14
#260
04
#261
b1000000000000000010000001 G
b11 N
b11 <
14
#262
04
#263
b100 <
b1000000000000000010000010 G
b100 N
14
#264
04
#265
b1000000000000000010000011 G
b101 N
b101 <
14
#266
04
#267
b110 <
b1000000000000000010000100 G
b110 N
14
#268
04
#269
b1000000000000000010000101 G
b111 N
b111 <
14
#270
04
#271
12
b1000 <
b1000000000000000010000110 G
1E
b1000 N
14
#272
04
#273
1&
1C
b1000000000000000010000111 G
0E
b1001 N
b1111111111111111111111111111111100000 P
b100000 L
b100000 R
b100010001000000001100000101000000 O
02
b1001 <
b11 V
b1 ,
b1 W
14
#274
04
#275
b1010 <
b1000000000000000010001000 G
b1010 N
14
#276
04
#277
b1000000000000000010001001 G
b1011 N
b1011 <
14
#278
04
#279
b1100 <
b1000000000000000010001010 G
b1100 N
14
#280
04
#281
b1000000000000000010001011 G
b1101 N
b1101 <
14
#282
04
#283
b1110 <
b1000000000000000010001100 G
b1110 N
14
#284
04
#285
b1000000000000000010001101 G
b1111 N
b1111 <
14
#286
04
1;
#287
1'
1@
13
b10000 <
b1000000000000000010001110 G
b10000 N
14
#288
04
#289
b11101 :
08
10
b1000000000000000010001111 G
b10001 N
b10001 <
1)
14
#290
04
#291
b10010 <
b1000000000000000010010000 G
b10010 N
14
#292
04
#293
b1000000000000000010010001 G
b10011 N
b10011 <
14
#294
04
#295
b10100 <
b1000000000000000010010010 G
b10100 N
14
#296
04
#297
b1000000000000000010010011 G
b10101 N
b10101 <
14
#298
04
#299
b10110 <
b1000000000000000010010100 G
b10110 N
14
#300
04
#301
b1000000000000000010010101 G
b10111 N
b10111 <
14
#302
04
#303
b11000 <
b1000000000000000010010110 G
b11000 N
14
#304
04
#305
b1000000000000000010010111 G
b11001 N
b11001 <
14
#306
04
#307
b11010 <
b1000000000000000010011000 G
b11010 N
14
#308
04
#309
b1000000000000000010011001 G
b11011 N
b11011 <
14
#310
04
#311
b11100 <
b1000000000000000010011010 G
b11100 N
14
#312
04
#313
b1000000000000000010011011 G
b11101 N
b11101 <
14
#314
04
#315
b11110 <
b1000000000000000010011100 G
b11110 N
14
#316
04
#317
b1000000000000000010011101 G
b11111 N
b11111 <
14
#318
04
#319
0'
0@
03
b0 <
b1000000000000000010011110 G
b0 N
14
#320
04
#321
00
b1000000000000000010011111 G
b1 N
b1 <
0)
14
#322
04
#323
b10 <
b1000000000000000010100000 G
b10 N
14
#324
04
#325
b1000000000000000010100001 G
b11 N
b11 <
14
#326
04
#327
b100 <
b1000000000000000010100010 G
b100 N
14
#328
04
#329
b1000000000000000010100011 G
b101 N
b101 <
14
#330
04
#331
b110 <
b1000000000000000010100100 G
b110 N
14
#332
04
#333
b1000000000000000010100101 G
b111 N
b111 <
14
#334
04
#335
12
b1000 <
b1000000000000000010100110 G
1E
b1000 N
14
#336
04
#337
0&
0C
b1000000000000000010100111 G
0E
b1001 N
b11111111111111111111111111111111000000 P
b1000000 L
b1000000 R
b100010000000011000001010000000 O
02
b1001 <
b100 V
b10 ,
b10 W
14
#338
04
#339
b1010 <
b1000000000000000010101000 G
b1010 N
14
#340
04
#341
b1000000000000000010101001 G
b1011 N
b1011 <
14
#342
04
#343
b1100 <
b1000000000000000010101010 G
b1100 N
14
#344
04
#345
b1000000000000000010101011 G
b1101 N
b1101 <
14
#346
04
#347
b1110 <
b1000000000000000010101100 G
b1110 N
14
#348
04
#349
b1000000000000000010101101 G
b1111 N
b1111 <
14
#350
04
#351
1'
1@
13
b10000 <
b1000000000000000010101110 G
b10000 N
14
#352
04
#353
b11100 :
10
b1000000000000000010101111 G
b10001 N
b10001 <
1)
14
#354
04
#355
b10010 <
b1000000000000000010110000 G
b10010 N
14
#356
04
#357
b1000000000000000010110001 G
b10011 N
b10011 <
14
#358
04
#359
b10100 <
b1000000000000000010110010 G
b10100 N
14
#360
04
#361
b1000000000000000010110011 G
b10101 N
b10101 <
14
#362
04
#363
b10110 <
b1000000000000000010110100 G
b10110 N
14
#364
04
#365
b1000000000000000010110101 G
b10111 N
b10111 <
14
#366
04
#367
b11000 <
b1000000000000000010110110 G
b11000 N
14
#368
04
#369
b1000000000000000010110111 G
b11001 N
b11001 <
14
#370
04
#371
b11010 <
b1000000000000000010111000 G
b11010 N
14
#372
04
#373
b1000000000000000010111001 G
b11011 N
b11011 <
14
#374
04
#375
b11100 <
b1000000000000000010111010 G
b11100 N
14
#376
04
#377
b1000000000000000010111011 G
b11101 N
b11101 <
14
#378
04
#379
b11110 <
b1000000000000000010111100 G
b11110 N
14
#380
04
#381
b1000000000000000010111101 G
b11111 N
b11111 <
14
#382
04
#383
0'
0@
03
b0 <
b1000000000000000010111110 G
b0 N
14
#384
04
#385
00
b1000000000000000010111111 G
b1 N
b1 <
0)
14
#386
04
#387
b10 <
b1000000000000000011000000 G
b10 N
14
#388
04
#389
b1000000000000000011000001 G
b11 N
b11 <
14
#390
04
#391
b100 <
b1000000000000000011000010 G
b100 N
14
#392
04
#393
b1000000000000000011000011 G
b101 N
b101 <
14
#394
04
#395
b110 <
b1000000000000000011000100 G
b110 N
14
#396
04
#397
b1000000000000000011000101 G
b111 N
b111 <
14
#398
04
#399
12
b1000 <
b1000000000000000011000110 G
1E
b1000 N
14
#400
04
#401
b1000000000000000011000111 G
0E
b1001 N
b111111111111111111111111111111110000000 P
b10000000 L
b10000000 R
b1000100000000110000010100000000 O
02
b1001 <
b101 V
b100 ,
b100 W
14
#402
04
#403
b1010 <
b1000000000000000011001000 G
b1010 N
14
#404
04
#405
b1000000000000000011001001 G
b1011 N
b1011 <
14
#406
04
#407
b1100 <
b1000000000000000011001010 G
b1100 N
14
#408
04
#409
b1000000000000000011001011 G
b1101 N
b1101 <
14
#410
04
#411
b1110 <
b1000000000000000011001100 G
b1110 N
14
#412
04
#413
b1000000000000000011001101 G
b1111 N
b1111 <
14
#414
04
#415
1'
1@
13
b10000 <
b1000000000000000011001110 G
b10000 N
14
#416
04
#417
b11011 :
10
b1000000000000000011001111 G
b10001 N
b10001 <
1)
14
#418
04
#419
b10010 <
b1000000000000000011010000 G
b10010 N
14
#420
04
#421
b1000000000000000011010001 G
b10011 N
b10011 <
14
#422
04
#423
b10100 <
b1000000000000000011010010 G
b10100 N
14
#424
04
#425
b1000000000000000011010011 G
b10101 N
b10101 <
14
#426
04
#427
b10110 <
b1000000000000000011010100 G
b10110 N
14
